logmongo
