Metadata-Version: 1.0
Name: logmongo
Version: 0.1.1
Summary: Logmongo: Log messages to a capped MongoDB collections
Home-page: https://bitbucket.org/russellballestrini/logmongo
Author: Russell Ballestrini
Author-email: russell@ballestrini.net
License: Public Domain
Keywords: Logmongo log dict messages mongo MongoDB
Platform: All
